{"_id":{"$oid":"5e148c942d1d04311c553fbc"},"id":"1","name":"New Model Winter Polar Jackets For Men","price":"2,299","image":"pimg1.jpg"}
{"_id":{"$oid":"5e148c942d1d04311c553fbd"},"id":"2","name":"Men's Warm Tirtleneck Sweater hombre Fashion ","price":"944","image":"pimg2.jpg"}
{"_id":{"$oid":"5e148c942d1d04311c553fbe"},"id":"3","name":"M1Full Ninja Mask With Air Filter ","price":"290","image":"pimg10.jpg"}
{"_id":{"$oid":"5e148c942d1d04311c553fbf"},"id":"4","name":"light Blue Inner fur jeans jacket For Men By Bajrang","price":"2,121","image":"pimg4.jpg"}
{"_id":{"$oid":"5e148c942d1d04311c553fc0"},"id":"5","name":"FreeFire Weekly Membership 420 Diamonds","price":"270","image":"pimg5.jpg"}
{"_id":{"$oid":"5e148c942d1d04311c553fc1"},"id":"6","name":"Solid Chest Guard Inside Polar For Warm- Unisex","price":"349","image":"pimg6.jpg"}
{"_id":{"$oid":"5e148c942d1d04311c553fc2"},"id":"7","name":"Lifetime Micrsoft Office 365(5devices mac/PC/ IOS/ Android)","price":"699","image":"pimg7.jpg"}
{"_id":{"$oid":"5e148c942d1d04311c553fc3"},"id":"8","name":"KEYI Electric Hot Bag (Colour Assorted)","price":"300","image":"pimg8.jpg"}
{"_id":{"$oid":"5e148c942d1d04311c553fc4"},"id":"9","name":"Nudge No Installation Need Faucet Electrical Instant Hot Water ","price":"3,499","image":"pimg9.jpg"}
{"_id":{"$oid":"5e148c942d1d04311c553fc5"},"id":"10","name":"Arrival Mart Summer Breathable Flying Woven","price":"4,200","image":"pimg10.jpg"}
{"_id":{"$oid":"5e148c942d1d04311c553fc6"},"id":"11","name":"New Black Riding PU Leather Jacket For Men","price":"3,650","image":"pimg11.jpg"}
{"_id":{"$oid":"5e148c942d1d04311c553fc7"},"id":"12","name":"J.Fisher Textured Fleece Oversize Pullover Hoodie For Women","price":"799","image":"pimg12.jpg"}
{"_id":{"$oid":"5e148c942d1d04311c553fc8"},"id":"13","name":"Golden Plated Long rani Haar Necklace With Earings For Women ","price":"2,500","image":"pimg13.jpg"}
{"_id":{"$oid":"5e148c942d1d04311c553fc9"},"id":"14","name":"Hifashion Combo Set Offer- Lightweight Unisex ","price":"1,599","image":"pimg14.jpg"}
{"_id":{"$oid":"5e148c942d1d04311c553fca"},"id":"15","name":"Pistto 100 Led, 10Meter Water Proof Starry Lights, Warm ","price":"899","image":"pimg15.jpg"}
{"_id":{"$oid":"5e148c942d1d04311c553fcb"},"id":"16","name":"Paldo Volcano Chicken Noodles(Limited Introduction)","price":"599","image":"pimg16.jpg"}
{"_id":{"$oid":"5e148c942d1d04311c553fcc"},"id":"17","name":"32GB MicroSD Pro Class 10 Memory Card","price":"1,499","image":"pimg17.jpg"}
{"_id":{"$oid":"5e148c942d1d04311c553fcd"},"id":"18","name":"EarPods with Remote and Mic-White","price":"650","image":"pimg18.jpg"}
{"_id":{"$oid":"5e148c942d1d04311c553fce"},"id":"19","name":"Long Olefin Hooded jacket For Women","price":"1,850","image":"pimg19.jpg"}
{"_id":{"$oid":"5e148c942d1d04311c553fcf"},"id":"20","name":"Samsung 8 Kg Fully- Automatic Front Loading Washing Machine","price":"69,990","image":"pimg20.jpg"}
{"_id":{"$oid":"5e148c942d1d04311c553fd0"},"id":"21","name":"New Model Winter Polar Jackets For Men","price":"Rs.2,299","image":"pimg1.jpg"}
{"_id":{"$oid":"5e148c942d1d04311c553fd1"},"id":"22","name":"Men's Warm Tirtleneck Sweater hombre Fashion ","price":"Rs.944","image":"pimg2.jpg"}
{"_id":{"$oid":"5e148c942d1d04311c553fd2"},"id":"23","name":"M1Full Ninja Mask With Air Filter ","price":"Rs.290","image":"pimg10.jpg"}
{"_id":{"$oid":"5e148c942d1d04311c553fd3"},"id":"24","name":"light Blue Inner fur jeans jacket For Men By Bajrang","price":"Rs.2,121","image":"pimg4.jpg"}
{"_id":{"$oid":"5e148c942d1d04311c553fd4"},"id":"25","name":"FreeFire Weekly Membership 420 Diamonds","price":"Rs.270","image":"pimg5.jpg"}
{"_id":{"$oid":"5e148c942d1d04311c553fd5"},"id":"26","name":"Solid Chest Guard Inside Polar For Warm- Unisex","price":"Rs.349","image":"pimg6.jpg"}
{"_id":{"$oid":"5e148c942d1d04311c553fd6"},"id":"27","name":"Lifetime Micrsoft Office 365(5devices mac/PC/ IOS/ Android)","price":"Rs.699","image":"pimg7.jpg"}
{"_id":{"$oid":"5e148c942d1d04311c553fd7"},"id":"28","name":"KEYI Electric Hot Bag (Colour Assorted)","price":"Rs.300","image":"pimg8.jpg"}
{"_id":{"$oid":"5e148c942d1d04311c553fd8"},"id":"29","name":"Nudge No Installation Need Faucet Electrical Instant Hot Water ","price":"Rs.3,499","image":"pimg9.jpg"}
{"_id":{"$oid":"5e148c942d1d04311c553fd9"},"id":"30","name":"Arrival Mart Summer Breathable Flying Woven","price":"Rs.4,200","image":"pimg10.jpg"}
{"_id":{"$oid":"5e148c942d1d04311c553fda"},"id":"31","name":"New Black Riding PU Leather Jacket For Men","price":"Rs.3,650","image":"pimg11.jpg"}
{"_id":{"$oid":"5e148c942d1d04311c553fdb"},"id":"32","name":"J.Fisher Textured Fleece Oversize Pullover Hoodie For Women","price":"Rs.799","image":"pimg12.jpg"}
{"_id":{"$oid":"5e148c942d1d04311c553fdc"},"id":"33","name":"Golden Plated Long rani Haar Necklace With Earings For Women ","price":"Rs.2,500","image":"pimg13.jpg"}
{"_id":{"$oid":"5e148c942d1d04311c553fdd"},"id":"34","name":"Hifashion Combo Set Offer- Lightweight Unisex ","price":"Rs.1,599","image":"pimg14.jpg"}
{"_id":{"$oid":"5e148c942d1d04311c553fde"},"id":"35","name":"Pistto 100 Led, 10Meter Water Proof Starry Lights, Warm ","price":"Rs.899","image":"pimg15.jpg"}
{"_id":{"$oid":"5e148c942d1d04311c553fdf"},"id":"36","name":"Paldo Volcano Chicken Noodles(Limited Introduction)","price":"Rs.599","image":"pimg16.jpg"}
{"_id":{"$oid":"5e148c942d1d04311c553fe0"},"id":"37","name":"32GB MicroSD Pro Class 10 Memory Card","price":"Rs.1,499","image":"pimg17.jpg"}
{"_id":{"$oid":"5e148c942d1d04311c553fe1"},"id":"38","name":"EarPods with Remote and Mic-White","price":"Rs.650","image":"pimg18.jpg"}
{"_id":{"$oid":"5e148c942d1d04311c553fe2"},"id":"39","name":"Long Olefin Hooded jacket For Women","price":"Rs.1,850","image":"pimg19.jpg"}
{"_id":{"$oid":"5e148c942d1d04311c553fe3"},"id":"40","name":"Samsung 8 Kg Fully- Automatic Front Loading Washing Machine","price":"Rs.69,990","image":"pimg20.jpg"}
